MANIFEST.in
README.rst
setup.py
tox.ini
admincommands/__init__.py
admincommands/admin.py
admincommands/apps.py
admincommands/models.py
admincommands/migrations/0001_initial.py
admincommands/migrations/__init__.py
django_admin_commands.egg-info/PKG-INFO
django_admin_commands.egg-info/SOURCES.txt
django_admin_commands.egg-info/dependency_links.txt
django_admin_commands.egg-info/requires.txt
django_admin_commands.egg-info/top_level.txt