Metadata-Version: 1.0
Name: django-admin-commands
Version: 0.91
Summary: Allow running Django management commands at the ease of your admin panel
Home-page: https://github.com/EralpB/django-admin-commands/
Author: Eralp Bayraktar
Author-email: imeralpb@gmail.com
License: MIT
Platform: UNKNOWN
